{
  "parent": "minecraft:recipes/root",
  "criteria": {
    "has_the_recipe": {
      "conditions": {
        "recipe": "minecraft:blazing_journal"
      },
      "trigger": "minecraft:recipe_unlocked"
    },
    "nothing": {
      "conditions": {
        "items": [
          {
            "items": [
              "minecraft:blaze_powder"
            ]
          }
        ]
      },
      "trigger": "minecraft:inventory_changed"
    }
  },
  "requirements": [
    [
      "nothing",
      "has_the_recipe"
    ]
  ],
  "rewards": {
    "recipes": [
      "minecraft:blazing_journal"
    ]
  },
  "sends_telemetry_event": false
}